[
  {
    "model": "workflows.abstractwidget", 
    "fields": {
      "category": "feb15899-59e3-46c8-994c-bbe806668fc8", 
      "treeview_image": "", 
      "uid": "16a08e1b-9c2a-4080-b45b-7d16ce3c5a24", 
      "windows_queue": false, 
      "package": "MUSE_v3", 
      "interaction_view": "", 
      "has_progress_bar": false, 
      "image": "", 
      "description": "Local copy of the 3D demonstrator for the Tuk the Hunter children story", 
      "static_image": "", 
      "action": "MUSE_virtual_environment_demonstrator_tuk_local_V3", 
      "visualization_view": "MUSE_virtual_environment_demonstrator_tuk_local_V3", 
      "streaming_visualization_view": "", 
      "post_interact_action": "", 
      "wsdl_method": "", 
      "wsdl": "", 
      "interactive": false, 
      "is_streaming": false, 
      "order": 1, 
      "name": "Tuk the Hunter 3D demonstrator (local)"
    }
  }, 
  {
    "model": "workflows.abstractinput", 
    "fields": {
      "widget": "16a08e1b-9c2a-4080-b45b-7d16ce3c5a24", 
      "name": "mapping file URL", 
      "short_name": "lnk", 
      "default": "", 
      "description": "A link to the XML file contating mapping to knowledge representation", 
      "required": true, 
      "multi": false, 
      "parameter_type": null, 
      "variable": "mappingLink", 
      "parameter": false, 
      "order": 1, 
      "uid": "7b6fff11-1076-44d1-a0f6-f6a1c196e9d7"
    }
  }, 
  {
    "model": "workflows.abstractinput", 
    "fields": {
      "widget": "16a08e1b-9c2a-4080-b45b-7d16ce3c5a24", 
      "name": "Unity3D app link", 
      "short_name": "lnk", 
      "default": "Tuk-Text-Workflow-Web.html", 
      "description": "A link to the Tuk Unity3D web app", 
      "required": true, 
      "multi": false, 
      "parameter_type": "text", 
      "variable": "unityLink", 
      "parameter": true, 
      "order": 2, 
      "uid": "867160f8-93e5-4a79-ab35-cb8577c4e98b"
    }
  }
]